fxxkpy/FullBaseObject.py
fxxkpy/FullFunction.py
fxxkpy/__hello__.py
fxxkpy/__init__.py
fxxkpy/_evaluate.py
fxxkpy/error.py
fxxkpy/game.py
fxxkpy/he.py
fxxkpy/languages.py
fxxkpy/math.py
fxxkpy/remove.py
fxxkpy/start.py
fxxkpy/vector.py
fxxkpy/version.py
fxxkpy/wallpaper.py
fxxkpy/JY/__init__.py
fxxkpy/JY/reference.py
fxxkpy/JY/start.py
fxxkpy/JY/version.py
fxxkpy/NaturalEngine/NaturalEngine.py
fxxkpy/NaturalEngine/__init__.py
fxxkpy/enigma/__init__.py
fxxkpy/enigma/data.py
fxxkpy/enigma/main.py
fxxkpy/enigma/static/404.html
fxxkpy/enigma/static/apply.html
fxxkpy/enigma/static/favicon.ico
fxxkpy/enigma/static/game.html
fxxkpy/enigma/static/index.html
fxxkpy/enigma/static/vue.js
fxxkpy/game/AircraftWar/LOGO.png
fxxkpy/game/AircraftWar/bg.jpg
fxxkpy/game/AircraftWar/bullet.png
fxxkpy/game/AircraftWar/enemy1.png
fxxkpy/game/AircraftWar/enemy1_down1.png
fxxkpy/game/AircraftWar/enemy1_down2.png
fxxkpy/game/AircraftWar/enemy1_down3.png
fxxkpy/game/AircraftWar/enemy1_down4.png
fxxkpy/game/AircraftWar/enemy1_down5.png
fxxkpy/game/AircraftWar/enemy2.png
fxxkpy/game/AircraftWar/enemy2_down1.png
fxxkpy/game/AircraftWar/enemy2_down2.png
fxxkpy/game/AircraftWar/enemy2_down3.png
fxxkpy/game/AircraftWar/enemy2_down4.png
fxxkpy/game/AircraftWar/enemy2_down5.png
fxxkpy/game/AircraftWar/enemy3.png
fxxkpy/game/AircraftWar/enemy3_1.png
fxxkpy/game/AircraftWar/enemy3_2.png
fxxkpy/game/AircraftWar/enemy3_down1.png
fxxkpy/game/AircraftWar/enemy3_down2.png
fxxkpy/game/AircraftWar/enemy3_down3.png
fxxkpy/game/AircraftWar/enemy3_down4.png
fxxkpy/game/AircraftWar/enemy3_down5.png
fxxkpy/game/AircraftWar/enemy3_down6.png
fxxkpy/game/AircraftWar/enemy3_down7.png
fxxkpy/game/AircraftWar/font.ttf
fxxkpy/game/AircraftWar/game_pause_nor.png
fxxkpy/game/AircraftWar/hero.png
fxxkpy/game/AircraftWar/hero_down1.png
fxxkpy/game/AircraftWar/hero_down2.png
fxxkpy/game/AircraftWar/hero_down3.png
fxxkpy/game/AircraftWar/hero_down4.png
fxxkpy/game/AircraftWar/over.png
fxxkpy/game/AircraftWar/score.png
fxxkpy-2.4.7.dist-info/LICENSE
fxxkpy-2.4.7.dist-info/METADATA
fxxkpy-2.4.7.dist-info/WHEEL
fxxkpy-2.4.7.dist-info/top_level.txt
fxxkpy-2.4.7.dist-info/RECORD
