Metadata-Version: 2.1
Name: fxxkpy
Version: 2.4.7
Summary: 这是一个中国人写的、非常棒的反Python库。
Home-page: https://github.com/SupJoN/fxxkpy
Author: SupJoN
Author-email: supjon@supjon.eu.org
Maintainer: SupJoN
License: MIT
Classifier: Development Status :: 5 - Production/Stable
Classifier: Natural Language :: Chinese (Simplified)
Classifier: Intended Audience :: Developers
Classifier: Topic :: Software Development
Classifier: Topic :: Software Development :: Libraries
Classifier: Topic :: Software Development :: Libraries :: Python Modules
Classifier: License :: OSI Approved :: MIT License
Classifier: Programming Language :: Python
Classifier: Programming Language :: Python :: 3
Classifier: Programming Language :: Python :: 3.10
Classifier: Programming Language :: Python :: 3.11
Classifier: Programming Language :: Python :: 3.12
Classifier: Programming Language :: Python :: Implementation :: CPython
Requires-Python: >=3.6.0
License-File: LICENSE
Requires-Dist: bottle
Requires-Dist: colorama
Requires-Dist: pygame
Requires-Dist: pywin32
Provides-Extra: look_better
Requires-Dist: rich ; extra == 'look_better'
Provides-Extra: more_support
Requires-Dist: fraction ; extra == 'more_support'
Requires-Dist: sympy ; extra == 'more_support'
